ddl_manager/README.md
ddl_manager/__init__.py
ddl_manager/__main__.py
ddl_manager/cli.py
ddl_manager/example/APPLY-000001-create_example_table.ddl
ddl_manager/example/APPLY-000002-add_example_column.ddl
ddl_manager/example/UNDO-000001-create_example_table.ddl
ddl_manager/example/UNDO-000002-add_example_column.ddl
postgres_pool/__init__.py
postgres_pool/database.py
the37lab_database_tools-0.1.1765798151.dist-info/METADATA
the37lab_database_tools-0.1.1765798151.dist-info/WHEEL
the37lab_database_tools-0.1.1765798151.dist-info/entry_points.txt
the37lab_database_tools-0.1.1765798151.dist-info/top_level.txt
the37lab_database_tools-0.1.1765798151.dist-info/RECORD
