Metadata-Version: 2.4
Name: the37lab_database_tools
Version: 0.1.1765798151
Summary: PostgreSQL database tools including DDL migration management and connection pooling
Author: the37Lab
License-Expression: LicenseRef-the37lab-Proprietary
Keywords: postgresql,database,migration,ddl,connection-pool
Classifier: Development Status :: 3 - Alpha
Classifier: Intended Audience :: Developers
Classifier: Programming Language :: Python :: 3.10
Classifier: Programming Language :: Python :: 3.11
Classifier: Programming Language :: Python :: 3.12
Classifier: Topic :: Database
Classifier: Topic :: Software Development :: Libraries :: Python Modules
Requires-Python: >=3.10
Requires-Dist: psycopg2-binary>=2.9.0
Provides-Extra: dev
Requires-Dist: pytest>=7.0.0; extra == "dev"
